setup.py
aiobeanstalk/__init__.py
aiobeanstalk/connection.py
aiobeanstalk/runner.py
aiobeanstalk.egg-info/PKG-INFO
aiobeanstalk.egg-info/SOURCES.txt
aiobeanstalk.egg-info/dependency_links.txt
aiobeanstalk.egg-info/requires.txt
aiobeanstalk.egg-info/top_level.txt