Metadata-Version: 1.1
Name: aiobeanstalk
Version: 0.0.2
Summary: asyncio based beanstalk client
Home-page: https://github.com/jonson/aiobeanstalk
Author: jonson
Author-email: UNKNOWN
License: UNKNOWN
Platform: UNKNOWN
Classifier: Programming Language :: Python :: 3.5
